xvs/__init__.py
xvs/vs.py
xvs-1.0.1.dist-info/METADATA
xvs-1.0.1.dist-info/WHEEL
xvs-1.0.1.dist-info/entry_points.txt
xvs-1.0.1.dist-info/top_level.txt
xvs-1.0.1.dist-info/RECORD
