Metadata-Version: 2.1
Name: xvs
Version: 1.0.1
Summary: A simple tool
Author: Ghost
Classifier: Programming Language :: Python :: 3
Classifier: License :: OSI Approved :: MIT License
Requires-Dist: requests
